msgflux/__init__.py
msgflux/cache.py
msgflux/dotdict.py
msgflux/envs.py
msgflux/examples.py
msgflux/exceptions.py
msgflux/logger.py
msgflux/message.py
msgflux/py.typed
msgflux/version.py
msgflux/_private/__init__.py
msgflux/_private/client.py
msgflux/_private/core.py
msgflux/_private/executor.py
msgflux/_private/response.py
msgflux/auto/__init__.py
msgflux/auto/params.py
msgflux/data/__init__.py
msgflux/data/audio.py
msgflux/data/dbs/__init__.py
msgflux/data/dbs/base.py
msgflux/data/dbs/db.py
msgflux/data/dbs/registry.py
msgflux/data/dbs/response.py
msgflux/data/dbs/types.py
msgflux/data/dbs/providers/__init__.py
msgflux/data/dbs/providers/cachetools.py
msgflux/data/dbs/providers/diskcache.py
msgflux/data/dbs/providers/faiss.py
msgflux/data/retrievers/__init__.py
msgflux/data/retrievers/base.py
msgflux/data/retrievers/registry.py
msgflux/data/retrievers/response.py
msgflux/data/retrievers/retriever.py
msgflux/data/retrievers/types.py
msgflux/data/retrievers/providers/__init__.py
msgflux/data/retrievers/providers/bm25.py
msgflux/data/retrievers/providers/rank_bm25.py
msgflux/data/retrievers/providers/wikipedia.py
msgflux/dsl/__init__.py
msgflux/dsl/inline.py
msgflux/dsl/signature.py
msgflux/dsl/typed_parsers/__init__.py
msgflux/dsl/typed_parsers/base.py
msgflux/dsl/typed_parsers/registry.py
msgflux/dsl/typed_parsers/providers/__init__.py
msgflux/dsl/typed_parsers/providers/xml.py
msgflux/generation/__init__.py
msgflux/generation/control_flow.py
msgflux/generation/templates.py
msgflux/generation/reasoning/__init__.py
msgflux/generation/reasoning/cot.py
msgflux/generation/reasoning/react.py
msgflux/generation/reasoning/self_consistency.py
msgflux/models/__init__.py
msgflux/models/base.py
msgflux/models/cache.py
msgflux/models/gateway.py
msgflux/models/httpx.py
msgflux/models/model.py
msgflux/models/registry.py
msgflux/models/response.py
msgflux/models/tool_call_agg.py
msgflux/models/types.py
msgflux/models/profiles/__init__.py
msgflux/models/profiles/base.py
msgflux-0.1.0a22.dist-info/METADATA
msgflux-0.1.0a22.dist-info/WHEEL
msgflux-0.1.0a22.dist-info/licenses/LICENSE
msgflux-0.1.0a22.dist-info/RECORD
